BacSC/ClusterDE.py
BacSC/NB_est.py
BacSC/__init__.py
BacSC/clustering_opt.py
BacSC/countsplit.py
BacSC/near_corr.py
BacSC/scDEED.py
BacSC/scTransform.py
BacSC/util.py
BacSC/util_probe.py
bacsc-0.1.1.dist-info/METADATA
bacsc-0.1.1.dist-info/WHEEL
bacsc-0.1.1.dist-info/licenses/LICENSE
bacsc-0.1.1.dist-info/RECORD
