Metadata-Version: 2.4
Name: BacSC
Version: 0.1.1
Summary: A general workflow for bacterial single-cell RNA sequencing data analysis
Project-URL: Homepage, https://github.com/bio-datascience/BacSC
Project-URL: Issues, https://github.com/bio-datascience/BacSC/issues
Author-email: Johannes Ostner <johannes.ostner@online.de>
License: MIT License
License-File: LICENSE
Classifier: Development Status :: 4 - Beta
Classifier: Framework :: Jupyter
Classifier: Intended Audience :: Developers
Classifier: Intended Audience :: Science/Research
Classifier: Natural Language :: English
Classifier: Operating System :: OS Independent
Classifier: Programming Language :: Python :: 3
Classifier: Topic :: Scientific/Engineering :: Bio-Informatics
Requires-Python: >=3.11
Requires-Dist: anndata
Requires-Dist: kdepy
Requires-Dist: leidenalg
Requires-Dist: matplotlib
Requires-Dist: numpy
Requires-Dist: pandas
Requires-Dist: scanpy
Requires-Dist: scipy
Requires-Dist: seaborn
Requires-Dist: statsmodels
Requires-Dist: venn
